odoo9_addon_openeducat_alumni-9.0.2.4.0-py2.7-nspkg.pth
odoo_addons/openeducat_alumni/__openerp__.py
odoo_addons/openeducat_alumni/__init__.py
odoo_addons/openeducat_alumni/models/alumni.py
odoo_addons/openeducat_alumni/models/__init__.py
odoo_addons/openeducat_alumni/i18n/openeducat_alumni.pot
odoo_addons/openeducat_alumni/views/alumni_view.xml
odoo_addons/openeducat_alumni/demo/op.student.csv
odoo_addons/openeducat_alumni/demo/op.roll.number.csv
odoo_addons/openeducat_alumni/demo/student_demo.xml
odoo_addons/openeducat_alumni/static/img/student_21.jpg
odoo_addons/openeducat_alumni/static/img/student_22.jpg
odoo_addons/openeducat_alumni/static/description/openeducat_logo.png
odoo_addons/openeducat_alumni/static/description/openeducat_alumni_banner.jpg
odoo_addons/openeducat_alumni/static/description/index.html
odoo_addons/openeducat_alumni/static/description/alumni.png
odoo_addons/openeducat_alumni/static/description/icon.png
odoo9_addon_openeducat_alumni-9.0.2.4.0.dist-info/top_level.txt
odoo9_addon_openeducat_alumni-9.0.2.4.0.dist-info/WHEEL
odoo9_addon_openeducat_alumni-9.0.2.4.0.dist-info/RECORD
odoo9_addon_openeducat_alumni-9.0.2.4.0.dist-info/metadata.json
odoo9_addon_openeducat_alumni-9.0.2.4.0.dist-info/DESCRIPTION.rst
odoo9_addon_openeducat_alumni-9.0.2.4.0.dist-info/METADATA
odoo9_addon_openeducat_alumni-9.0.2.4.0.dist-info/namespace_packages.txt
